{
  "post": [
    {
      "category": "category 4",
      "name": "gdfgdfg4",
      "text": "4fdfdfdfdf",
      "id": 4
    },
    {
      "name": "category 3",
      "text": "category 3",
      "category": "category 3",
      "id": 25
    },
    {
      "name": "Nastya",
      "text": "skdkslls",
      "category": "Test 222222",
      "id": 27
    },
    {
      "name": "Nastya 1111",
      "text": "skdksllsafdlkdl;dsl;'dsc",
      "category": "Test 1 4444",
      "id": 30
    },
    {
      "name": "іівів",
      "text": "іввв",
      "category": "вдвдж",
      "id": 34
    },
    {
      "name": "ss",
      "text": "ss",
      "category": "sss",
      "id": 35
    },
    {
      "name": "fdsfsdf",
      "text": "sdfsdf",
      "category": "dvsf",
      "id": 39
    },
    {
      "name": "fdsfsdf",
      "text": "sdfsdf",
      "category": "dvsf",
      "id": 40
    },
    {
      "name": "Nastya",
      "text": "d",
      "category": "sssd",
      "id": 45
    },
    {
      "name": "Name 1",
      "text": "Text 1 ",
      "category": "Category 1",
      "id": 46
    },
    {
      "name": "Name 2",
      "text": "Text 2",
      "category": "Category 2",
      "id": 47
    }
  ]
}